<annotation verified="yes">
	<folder>covers</folder>
	<filename>Abola_2019-06-17.jpeg</filename>
	<path>Abola_2019-06-17.jpeg</path>
	<source>
		<database>Unknown</database>
	</source>
	<size>
		<width>1050</width>
		<height>1317</height>
		<depth>3</depth>
	</size>
	<segmented>0</segmented>
	<object>
		<name>PUB</name>
		<pose>Unspecified</pose>
		<truncated>0</truncated>
		<difficult>0</difficult>
		<bndbox>
			<xmin>14</xmin>
			<ymin>1204</ymin>
			<xmax>1044</xmax>
			<ymax>1316</ymax>
		</bndbox>
	</object>
	<object>
		<name>BENFICA</name>
		<pose>Unspecified</pose>
		<truncated>0</truncated>
		<difficult>0</difficult>
		<bndbox>
			<xmin>852</xmin>
			<ymin>13</ymin>
			<xmax>1049</xmax>
			<ymax>176</ymax>
		</bndbox>
	</object>
	<object>
		<name>PORTO</name>
		<pose>Unspecified</pose>
		<truncated>0</truncated>
		<difficult>0</difficult>
		<bndbox>
			<xmin>221</xmin>
			<ymin>965</ymin>
			<xmax>413</xmax>
			<ymax>1191</ymax>
		</bndbox>
	</object>
	<object>
		<name>SPORTING</name>
		<pose>Unspecified</pose>
		<truncated>0</truncated>
		<difficult>0</difficult>
		<bndbox>
			<xmin>433</xmin>
			<ymin>966</ymin>
			<xmax>626</xmax>
			<ymax>1188</ymax>
		</bndbox>
	</object>
	<object>
		<name>BENFICA</name>
		<pose>Unspecified</pose>
		<truncated>0</truncated>
		<difficult>0</difficult>
		<bndbox>
			<xmin>12</xmin>
			<ymin>965</ymin>
			<xmax>203</xmax>
			<ymax>1187</ymax>
		</bndbox>
	</object>
	<object>
		<name>OTHER</name>
		<pose>Unspecified</pose>
		<truncated>0</truncated>
		<difficult>0</difficult>
		<bndbox>
			<xmin>642</xmin>
			<ymin>964</ymin>
			<xmax>1044</xmax>
			<ymax>1183</ymax>
		</bndbox>
	</object>
	<object>
		<name>BENFICA</name>
		<pose>Unspecified</pose>
		<truncated>0</truncated>
		<difficult>0</difficult>
		<bndbox>
			<xmin>9</xmin>
			<ymin>184</ymin>
			<xmax>1044</xmax>
			<ymax>948</ymax>
		</bndbox>
	</object>
	<object>
		<name>SPORTING</name>
		<pose>Unspecified</pose>
		<truncated>0</truncated>
		<difficult>0</difficult>
		<bndbox>
			<xmin>7</xmin>
			<ymin>182</ymin>
			<xmax>1042</xmax>
			<ymax>946</ymax>
		</bndbox>
	</object>
</annotation>
