<annotation verified="yes">
	<folder>covers</folder>
	<filename>Abola_2019-09-12.jpeg</filename>
	<path>Abola_2019-09-12.jpeg</path>
	<source>
		<database>Unknown</database>
	</source>
	<size>
		<width>1050</width>
		<height>1280</height>
		<depth>3</depth>
	</size>
	<segmented>0</segmented>
	<object>
		<name>PUB</name>
		<pose>Unspecified</pose>
		<truncated>0</truncated>
		<difficult>0</difficult>
		<bndbox>
			<xmin>33</xmin>
			<ymin>1171</ymin>
			<xmax>1042</xmax>
			<ymax>1278</ymax>
		</bndbox>
	</object>
	<object>
		<name>PUB</name>
		<pose>Unspecified</pose>
		<truncated>0</truncated>
		<difficult>0</difficult>
		<bndbox>
			<xmin>32</xmin>
			<ymin>10</ymin>
			<xmax>1039</xmax>
			<ymax>114</ymax>
		</bndbox>
	</object>
	<object>
		<name>SPORTING</name>
		<pose>Unspecified</pose>
		<truncated>0</truncated>
		<difficult>0</difficult>
		<bndbox>
			<xmin>32</xmin>
			<ymin>302</ymin>
			<xmax>222</xmax>
			<ymax>915</ymax>
		</bndbox>
	</object>
	<object>
		<name>OTHER</name>
		<pose>Unspecified</pose>
		<truncated>0</truncated>
		<difficult>0</difficult>
		<bndbox>
			<xmin>32</xmin>
			<ymin>922</ymin>
			<xmax>220</xmax>
			<ymax>1102</ymax>
		</bndbox>
	</object>
	<object>
		<name>BENFICA</name>
		<pose>Unspecified</pose>
		<truncated>0</truncated>
		<difficult>0</difficult>
		<bndbox>
			<xmin>852</xmin>
			<ymin>434</ymin>
			<xmax>1041</xmax>
			<ymax>775</ymax>
		</bndbox>
	</object>
	<object>
		<name>PORTO</name>
		<pose>Unspecified</pose>
		<truncated>0</truncated>
		<difficult>0</difficult>
		<bndbox>
			<xmin>852</xmin>
			<ymin>134</ymin>
			<xmax>1044</xmax>
			<ymax>433</ymax>
		</bndbox>
	</object>
	<object>
		<name>BENFICA</name>
		<pose>Unspecified</pose>
		<truncated>0</truncated>
		<difficult>0</difficult>
		<bndbox>
			<xmin>238</xmin>
			<ymin>300</ymin>
			<xmax>836</xmax>
			<ymax>1102</ymax>
		</bndbox>
	</object>
	<object>
		<name>OTHER</name>
		<pose>Unspecified</pose>
		<truncated>0</truncated>
		<difficult>0</difficult>
		<bndbox>
			<xmin>30</xmin>
			<ymin>1110</ymin>
			<xmax>848</xmax>
			<ymax>1163</ymax>
		</bndbox>
	</object>
</annotation>
