<annotation verified="yes">
	<folder>covers</folder>
	<filename>Ojogo_2019-10-03.jpeg</filename>
	<path>Ojogo_2019-10-03.jpeg</path>
	<source>
		<database>Unknown</database>
	</source>
	<size>
		<width>1050</width>
		<height>1246</height>
		<depth>3</depth>
	</size>
	<segmented>0</segmented>
	<object>
		<name>PUB</name>
		<pose>Unspecified</pose>
		<truncated>0</truncated>
		<difficult>0</difficult>
		<bndbox>
			<xmin>47</xmin>
			<ymin>9</ymin>
			<xmax>1035</xmax>
			<ymax>111</ymax>
		</bndbox>
	</object>
	<object>
		<name>BENFICA</name>
		<pose>Unspecified</pose>
		<truncated>0</truncated>
		<difficult>0</difficult>
		<bndbox>
			<xmin>356</xmin>
			<ymin>175</ymin>
			<xmax>1035</xmax>
			<ymax>988</ymax>
		</bndbox>
	</object>
	<object>
		<name>PORTO</name>
		<pose>Unspecified</pose>
		<truncated>0</truncated>
		<difficult>0</difficult>
		<bndbox>
			<xmin>47</xmin>
			<ymin>693</ymin>
			<xmax>327</xmax>
			<ymax>1025</ymax>
		</bndbox>
	</object>
	<object>
		<name>OTHER</name>
		<pose>Unspecified</pose>
		<truncated>0</truncated>
		<difficult>0</difficult>
		<bndbox>
			<xmin>355</xmin>
			<ymin>1002</ymin>
			<xmax>505</xmax>
			<ymax>1122</ymax>
		</bndbox>
	</object>
	<object>
		<name>SPORTING</name>
		<pose>Unspecified</pose>
		<truncated>0</truncated>
		<difficult>0</difficult>
		<bndbox>
			<xmin>518</xmin>
			<ymin>1003</ymin>
			<xmax>868</xmax>
			<ymax>1121</ymax>
		</bndbox>
	</object>
	<object>
		<name>OTHER</name>
		<pose>Unspecified</pose>
		<truncated>0</truncated>
		<difficult>0</difficult>
		<bndbox>
			<xmin>884</xmin>
			<ymin>1002</ymin>
			<xmax>1037</xmax>
			<ymax>1124</ymax>
		</bndbox>
	</object>
	<object>
		<name>PUB</name>
		<pose>Unspecified</pose>
		<truncated>0</truncated>
		<difficult>0</difficult>
		<bndbox>
			<xmin>45</xmin>
			<ymin>1139</ymin>
			<xmax>1033</xmax>
			<ymax>1240</ymax>
		</bndbox>
	</object>
	<object>
		<name>OTHER</name>
		<pose>Unspecified</pose>
		<truncated>0</truncated>
		<difficult>0</difficult>
		<bndbox>
			<xmin>45</xmin>
			<ymin>1033</ymin>
			<xmax>327</xmax>
			<ymax>1124</ymax>
		</bndbox>
	</object>
</annotation>
